open_alchemy/__init__.py
open_alchemy/package_database/__init__.py
open_alchemy/package_database/config.py
open_alchemy/package_database/dynamodb.py
open_alchemy/package_database/exceptions.py
open_alchemy/package_database/factory.py
open_alchemy/package_database/init-database.js
open_alchemy/package_database/models.py
open_alchemy/package_database/pytest_plugin.py
open_alchemy/package_database/types.py
open_alchemy.package_database-4.0.1.dist-info/entry_points.txt
open_alchemy.package_database-4.0.1.dist-info/WHEEL
open_alchemy.package_database-4.0.1.dist-info/METADATA
open_alchemy.package_database-4.0.1.dist-info/RECORD
