Metadata-Version: 2.1
Name: open-alchemy.package-database
Version: 4.0.1
Summary: Facade for the OpenAlchemy package database
License: Apache-2.0
Author: David Andersson
Author-email: jdkandersson@users.noreply.github.com
Requires-Python: >=3.8,<4.0
Classifier: License :: OSI Approved :: Apache Software License
Classifier: Programming Language :: Python :: 3
Classifier: Programming Language :: Python :: 3.8
Classifier: Programming Language :: Python :: 3.9
Requires-Dist: packaging (>=20.8,<21.0)
Requires-Dist: pynamodb (>=4.3.3,<5.0.0)
